{
  "version": "1.0.0",
  "restore": {
    "projectUniqueName": "/media/stefan/AA2ECBB72ECB7AB9/Users/Stefan/Desktop/PSBD-Proiect/IaSiViziteaza.FE/IaSiViziteaza.FE.csproj",
    "projectName": "IaSiViziteaza.FE",
    "projectPath": "/media/stefan/AA2ECBB72ECB7AB9/Users/Stefan/Desktop/PSBD-Proiect/IaSiViziteaza.FE/IaSiViziteaza.FE.csproj",
    "outputPath": "/media/stefan/AA2ECBB72ECB7AB9/Users/Stefan/Desktop/PSBD-Proiect/IaSiViziteaza.FE/obj/",
    "projectStyle": "PackageReference",
    "originalTargetFrameworks": [
      "netcoreapp2.2"
    ],
    "sources": {
      "https://api.nuget.org/v3/index.json": {}
    },
    "frameworks": {
      "netcoreapp2.2": {
        "projectReferences": {}
      }
    },
    "warningProperties": {
      "warnAsError": [
        "NU1605"
      ]
    }
  },
  "frameworks": {
    "netcoreapp2.2": {
      "dependencies": {
        "Microsoft.AspNetCore.App": {
          "suppressParent": "All",
          "target": "Package",
          "version": "[2.2.0, )",
          "autoReferenced": true
        },
        "Microsoft.AspNetCore.Razor.Design": {
          "suppressParent": "All",
          "target": "Package",
          "version": "[2.2.0, )"
        },
        "Microsoft.NETCore.App": {
          "suppressParent": "All",
          "target": "Package",
          "version": "[2.2.0, )",
          "autoReferenced": true
        }
      },
      "imports": [
        "net461",
        "net462",
        "net47",
        "net471",
        "net472",
        "net48"
      ],
      "assetTargetFallback": true,
      "warn": true
    }
  }
}